{"config":{"output_file":null,"full_docs":false,"pub_only":false,"reachable_only":false,"distro_crate":false,"signatures":false,"borrow_data":false},"version":"0.19.0","compilation":{"directory":"/home/prafulla/Documents/RustPractice/guessing_game","program":"/home/prafulla/.rustup/toolchains/stable-x86_64-unknown-linux-gnu/bin/rls","arguments":[],"output":"/home/prafulla/Documents/RustPractice/guessing_game/target/rls/debug/deps/libguessing_game-a7f4c8c042c37a73.rmeta"},"prelude":{"crate_id":{"name":"guessing_game","disambiguator":[9693245820486188404,4780932268827844663]},"crate_root":"src","external_crates":[{"file_name":"/home/prafulla/Documents/RustPractice/guessing_game/src/main.rs","num":1,"id":{"name":"std","disambiguator":[12673765241971086519,1979875191208036248]}},{"file_name":"/home/prafulla/Documents/RustPractice/guessing_game/src/main.rs","num":2,"id":{"name":"core","disambiguator":[16221439354469382097,15565837348772828253]}},{"file_name":"/home/prafulla/Documents/RustPractice/guessing_game/src/main.rs","num":3,"id":{"name":"compiler_builtins","disambiguator":[15613252303691562375,4556165055238676072]}},{"file_name":"/home/prafulla/Documents/RustPractice/guessing_game/src/main.rs","num":4,"id":{"name":"rustc_std_workspace_core","disambiguator":[12269617896898487533,65142111397584226]}},{"file_name":"/home/prafulla/Documents/RustPractice/guessing_game/src/main.rs","num":5,"id":{"name":"alloc","disambiguator":[15862783141653200230,4773813417861420487]}},{"file_name":"/home/prafulla/Documents/RustPractice/guessing_game/src/main.rs","num":6,"id":{"name":"libc","disambiguator":[501305773035659233,3889300012469539238]}},{"file_name":"/home/prafulla/Documents/RustPractice/guessing_game/src/main.rs","num":7,"id":{"name":"unwind","disambiguator":[9126002216567348836,15610270334556716503]}},{"file_name":"/home/prafulla/Documents/RustPractice/guessing_game/src/main.rs","num":8,"id":{"name":"cfg_if","disambiguator":[9479301707518706798,13352731276321566042]}},{"file_name":"/home/prafulla/Documents/RustPractice/guessing_game/src/main.rs","num":9,"id":{"name":"backtrace","disambiguator":[15203654865662241151,17897348793673631766]}},{"file_name":"/home/prafulla/Documents/RustPractice/guessing_game/src/main.rs","num":10,"id":{"name":"rustc_demangle","disambiguator":[10290502124864695413,7672610073830174493]}},{"file_name":"/home/prafulla/Documents/RustPractice/guessing_game/src/main.rs","num":11,"id":{"name":"backtrace_sys","disambiguator":[14838544226648722576,13006716085524361330]}},{"file_name":"/home/prafulla/Documents/RustPractice/guessing_game/src/main.rs","num":12,"id":{"name":"hashbrown","disambiguator":[9246889555580827340,16878203682218964580]}},{"file_name":"/home/prafulla/Documents/RustPractice/guessing_game/src/main.rs","num":13,"id":{"name":"rustc_std_workspace_alloc","disambiguator":[8284748314555817558,4769950866534510046]}},{"file_name":"/home/prafulla/Documents/RustPractice/guessing_game/src/main.rs","num":14,"id":{"name":"panic_unwind","disambiguator":[14671874173783541769,17969261176539820175]}},{"file_name":"/home/prafulla/Documents/RustPractice/guessing_game/src/main.rs","num":15,"id":{"name":"test","disambiguator":[9313540940719435894,6433276621802240045]}},{"file_name":"/home/prafulla/Documents/RustPractice/guessing_game/src/main.rs","num":16,"id":{"name":"getopts","disambiguator":[15940589346932726858,6348868037951525207]}},{"file_name":"/home/prafulla/Documents/RustPractice/guessing_game/src/main.rs","num":17,"id":{"name":"rustc_std_workspace_std","disambiguator":[14241386022437774139,9978606192486280148]}},{"file_name":"/home/prafulla/Documents/RustPractice/guessing_game/src/main.rs","num":18,"id":{"name":"unicode_width","disambiguator":[3855268850323942265,13067211433436981736]}},{"file_name":"/home/prafulla/Documents/RustPractice/guessing_game/src/main.rs","num":19,"id":{"name":"term","disambiguator":[9878895306989019843,2899800260231466794]}}],"span":{"file_name":"src/main.rs","byte_start":0,"byte_end":1326,"line_start":1,"line_end":29,"column_start":1,"column_end":2}},"imports":[{"kind":"Use","ref_id":{"krate":1,"index":2274},"span":{"file_name":"src/main.rs","byte_start":9,"byte_end":11,"line_start":1,"line_end":1,"column_start":10,"column_end":12},"alias_span":null,"name":"io","value":"","parent":{"krate":0,"index":0}}],"defs":[{"kind":"Mod","id":{"krate":0,"index":0},"span":{"file_name":"src/main.rs","byte_start":0,"byte_end":1326,"line_start":1,"line_end":29,"column_start":1,"column_end":2},"name":"","qualname":"::","value":"src/main.rs","parent":null,"children":[{"krate":0,"index":1},{"krate":0,"index":2},{"krate":0,"index":3},{"krate":0,"index":4},{"krate":0,"index":5}],"decl_id":null,"docs":"","sig":null,"attributes":[]},{"kind":"Function","id":{"krate":0,"index":4},"span":{"file_name":"src/main.rs","byte_start":17,"byte_end":21,"line_start":3,"line_end":3,"column_start":4,"column_end":8},"name":"main","qualname":"::main","value":"fn () -> ()","parent":null,"children":[],"decl_id":null,"docs":"","sig":null,"attributes":[{"value":"allow(dead_code)","span":{"file_name":"src/main.rs","byte_start":0,"byte_end":0,"line_start":1,"line_end":1,"column_start":1,"column_end":1}}]},{"kind":"Local","id":{"krate":0,"index":4294967277},"span":{"file_name":"src/main.rs","byte_start":114,"byte_end":119,"line_start":7,"line_end":7,"column_start":13,"column_end":18},"name":"guess","qualname":"guess$18","value":"std::string::String","parent":null,"children":[],"decl_id":null,"docs":"","sig":null,"attributes":[]},{"kind":"Local","id":{"krate":0,"index":4294967271},"span":{"file_name":"src/main.rs","byte_start":338,"byte_end":344,"line_start":10,"line_end":10,"column_start":9,"column_end":15},"name":"std_in","qualname":"std_in$24","value":"std::io::Stdin","parent":null,"children":[],"decl_id":null,"docs":"","sig":null,"attributes":[]},{"kind":"Local","id":{"krate":0,"index":4294967262},"span":{"file_name":"src/main.rs","byte_start":463,"byte_end":469,"line_start":11,"line_end":11,"column_start":9,"column_end":15},"name":"result","qualname":"result$33","value":"std::result::Result<usize, std::io::Error>","parent":null,"children":[],"decl_id":null,"docs":"","sig":null,"attributes":[]},{"kind":"Local","id":{"krate":0,"index":4294967248},"span":{"file_name":"src/main.rs","byte_start":620,"byte_end":631,"line_start":12,"line_end":12,"column_start":9,"column_end":20},"name":"string_size","qualname":"string_size$47","value":"usize","parent":null,"children":[],"decl_id":null,"docs":"","sig":null,"attributes":[]}],"impls":[],"refs":[{"kind":"Mod","span":{"file_name":"src/main.rs","byte_start":4,"byte_end":7,"line_start":1,"line_end":1,"column_start":5,"column_end":8},"ref_id":{"krate":1,"index":0}},{"kind":"Function","span":{"file_name":"src/main.rs","byte_start":130,"byte_end":133,"line_start":7,"line_end":7,"column_start":29,"column_end":32},"ref_id":{"krate":5,"index":3546}},{"kind":"Type","span":{"file_name":"src/main.rs","byte_start":122,"byte_end":128,"line_start":7,"line_end":7,"column_start":21,"column_end":27},"ref_id":{"krate":5,"index":4867}},{"kind":"Type","span":{"file_name":"src/main.rs","byte_start":350,"byte_end":355,"line_start":10,"line_end":10,"column_start":21,"column_end":26},"ref_id":{"krate":1,"index":2722}},{"kind":"Mod","span":{"file_name":"src/main.rs","byte_start":346,"byte_end":348,"line_start":10,"line_end":10,"column_start":17,"column_end":19},"ref_id":{"krate":1,"index":2274}},{"kind":"Function","span":{"file_name":"src/main.rs","byte_start":362,"byte_end":367,"line_start":10,"line_end":10,"column_start":33,"column_end":38},"ref_id":{"krate":1,"index":2727}},{"kind":"Mod","span":{"file_name":"src/main.rs","byte_start":358,"byte_end":360,"line_start":10,"line_end":10,"column_start":29,"column_end":31},"ref_id":{"krate":1,"index":2274}},{"kind":"Type","span":{"file_name":"src/main.rs","byte_start":475,"byte_end":481,"line_start":11,"line_end":11,"column_start":21,"column_end":27},"ref_id":{"krate":1,"index":2503}},{"kind":"Mod","span":{"file_name":"src/main.rs","byte_start":471,"byte_end":473,"line_start":11,"line_end":11,"column_start":17,"column_end":19},"ref_id":{"krate":1,"index":2274}},{"kind":"Function","span":{"file_name":"src/main.rs","byte_start":498,"byte_end":507,"line_start":11,"line_end":11,"column_start":44,"column_end":53},"ref_id":{"krate":1,"index":2733}},{"kind":"Variable","span":{"file_name":"src/main.rs","byte_start":491,"byte_end":497,"line_start":11,"line_end":11,"column_start":37,"column_end":43},"ref_id":{"krate":0,"index":4294967271}},{"kind":"Variable","span":{"file_name":"src/main.rs","byte_start":513,"byte_end":518,"line_start":11,"line_end":11,"column_start":59,"column_end":64},"ref_id":{"krate":0,"index":4294967277}},{"kind":"Function","span":{"file_name":"src/main.rs","byte_start":648,"byte_end":654,"line_start":12,"line_end":12,"column_start":37,"column_end":43},"ref_id":{"krate":2,"index":5582}},{"kind":"Variable","span":{"file_name":"src/main.rs","byte_start":641,"byte_end":647,"line_start":12,"line_end":12,"column_start":30,"column_end":36},"ref_id":{"krate":0,"index":4294967262}},{"kind":"Variable","span":{"file_name":"src/main.rs","byte_start":993,"byte_end":1004,"line_start":20,"line_end":20,"column_start":8,"column_end":19},"ref_id":{"krate":0,"index":4294967248}},{"kind":"Function","span":{"file_name":"src/main.rs","byte_start":1014,"byte_end":1017,"line_start":20,"line_end":20,"column_start":29,"column_end":32},"ref_id":{"krate":5,"index":3581}},{"kind":"Variable","span":{"file_name":"src/main.rs","byte_start":1008,"byte_end":1013,"line_start":20,"line_end":20,"column_start":23,"column_end":28},"ref_id":{"krate":0,"index":4294967277}},{"kind":"Variable","span":{"file_name":"src/main.rs","byte_start":1274,"byte_end":1279,"line_start":26,"line_end":26,"column_start":33,"column_end":38},"ref_id":{"krate":0,"index":4294967277}},{"kind":"Variable","span":{"file_name":"src/main.rs","byte_start":1315,"byte_end":1320,"line_start":27,"line_end":27,"column_start":33,"column_end":38},"ref_id":{"krate":0,"index":4294967277}}],"macro_refs":[],"relations":[]}